cortex_mapping/__init__.py
cortex_mapping/main.py
cortex_mapping/mapping.py
cortex_mapping/data/networks.32k.L.label.gii
cortex_mapping/data/networks.32k.R.label.gii
cortex_mapping/data/networks_table.csv
feature_extraction/__init__.py
feature_extraction/clusters.py
feature_extraction/connectivity.py
feature_extraction/parcellation_overlap.py
feature_extraction/pipeline.py
feature_extraction/sharpness.py
feature_extraction/surface_area.py
feature_extraction/utils.py
hipp_mapping/__init__.py
hipp_mapping/main.py
hipp_mapping/mapping.py
hipp_mapping/data/template.L.shape.gii
hipp_mapping/data/template.R.shape.gii
precision_mapping-2.1.2.dist-info/METADATA
precision_mapping-2.1.2.dist-info/WHEEL
precision_mapping-2.1.2.dist-info/entry_points.txt
precision_mapping-2.1.2.dist-info/top_level.txt
precision_mapping-2.1.2.dist-info/RECORD
